setup.py
ginger/__init__.py
ginger/__main__.py
ginger/build.py
ginger/conf.py
ginger.egg-info/PKG-INFO
ginger.egg-info/SOURCES.txt
ginger.egg-info/dependency_links.txt
ginger.egg-info/entry_points.txt
ginger.egg-info/requires.txt
ginger.egg-info/top_level.txt
input/__init__.py