Metadata-Version: 1.0
Name: ginger
Version: 0.0.3
Summary: A very lightweight static site generator
Home-page: https://github.com/DistilledLtd/ginger
Author: Distilled Ltd
Author-email: randd@distilled.net
License: UNKNOWN
Platform: UNKNOWN
